{
  "date" : "Tue, 06 Jan, 2026 16:33:10 +0000",
  "doco" : "For each file: start is seconds after start activity occurred. Length = milliseconds activity took",
  "files" : [
    {
      "name" : "/fsh-generated/resources/ImplementationGuide-fhir.ig.demo.json",
      "size" : 10135,
      "processes" : [
        {
          "activity" : "load",
          "start" : 28,
          "length" : 9
        },
        {
          "activity" : "checkR4R4B",
          "start" : 28,
          "length" : 10
        },
        {
          "activity" : "generateNarratives",
          "start" : 28,
          "length" : 90
        },
        {
          "activity" : "validate",
          "start" : 42,
          "length" : 2815
        },
        {
          "activity" : "generate1",
          "start" : 47,
          "length" : 76
        },
        {
          "activity" : "generate2",
          "start" : 52,
          "length" : 74
        },
        {
          "activity" : "generateValidationPack",
          "start" : 65,
          "length" : 2
        },
        {
          "activity" : "scanExamplesForR5",
          "start" : 74,
          "length" : 1
        }
      ]
    },
    {
      "name" : "fsh-generated/resources/CodeSystem-LGIdTypeCS.json",
      "size" : 632,
      "processes" : [
        {
          "activity" : "loadResources",
          "start" : 27,
          "length" : 25
        },
        {
          "activity" : "load",
          "start" : 28,
          "length" : 3
        },
        {
          "activity" : "generateNarratives",
          "start" : 28,
          "length" : 18
        },
        {
          "activity" : "validate",
          "start" : 33,
          "length" : 11
        },
        {
          "activity" : "generate1",
          "start" : 48,
          "length" : 15
        },
        {
          "activity" : "generate2",
          "start" : 52,
          "length" : 669
        }
      ]
    },
    {
      "name" : "fsh-generated/resources/CodeSystem-LLIdTypeCS.json",
      "size" : 684,
      "processes" : [
        {
          "activity" : "loadResources",
          "start" : 28,
          "length" : 12
        },
        {
          "activity" : "load",
          "start" : 28,
          "length" : 3
        },
        {
          "activity" : "checkR4R4B",
          "start" : 28,
          "length" : 1
        },
        {
          "activity" : "generateNarratives",
          "start" : 28,
          "length" : 14
        },
        {
          "activity" : "validate",
          "start" : 33,
          "length" : 7
        },
        {
          "activity" : "generate1",
          "start" : 48,
          "length" : 15
        },
        {
          "activity" : "generate2",
          "start" : 52,
          "length" : 95
        }
      ]
    },
    {
      "name" : "fsh-generated/resources/CodeSystem-RxVXIdTypeCS.json",
      "size" : 603,
      "processes" : [
        {
          "activity" : "loadResources",
          "start" : 28,
          "length" : 3
        },
        {
          "activity" : "load",
          "start" : 28,
          "length" : 3
        },
        {
          "activity" : "generateNarratives",
          "start" : 28,
          "length" : 14
        },
        {
          "activity" : "validate",
          "start" : 33,
          "length" : 7
        },
        {
          "activity" : "generate1",
          "start" : 48,
          "length" : 13
        },
        {
          "activity" : "generate2",
          "start" : 52,
          "length" : 77
        }
      ]
    },
    {
      "name" : "fsh-generated/resources/NamingSystem-HHIdNS.json",
      "size" : 410,
      "processes" : [
        {
          "activity" : "loadResources",
          "start" : 28,
          "length" : 5
        },
        {
          "activity" : "load",
          "start" : 28,
          "length" : 4
        },
        {
          "activity" : "load-configure",
          "start" : 28,
          "length" : 1
        },
        {
          "activity" : "generateNarratives",
          "start" : 28,
          "length" : 16
        },
        {
          "activity" : "validate",
          "start" : 33,
          "length" : 27
        },
        {
          "activity" : "generate1",
          "start" : 48,
          "length" : 13
        },
        {
          "activity" : "generate2",
          "start" : 52,
          "length" : 12
        }
      ]
    },
    {
      "name" : "fsh-generated/resources/Observation-App1ObservationExample.json",
      "size" : 789,
      "processes" : [
        {
          "activity" : "loadResources",
          "start" : 28,
          "length" : 6
        },
        {
          "activity" : "generateNarratives",
          "start" : 28,
          "length" : 1853
        },
        {
          "activity" : "validate",
          "start" : 45,
          "length" : 621
        },
        {
          "activity" : "generate1",
          "start" : 48,
          "length" : 13
        },
        {
          "activity" : "generate2",
          "start" : 52,
          "length" : 18
        }
      ]
    },
    {
      "name" : "fsh-generated/resources/Observation-App2ObservationExample.json",
      "size" : 973,
      "processes" : [
        {
          "activity" : "loadResources",
          "start" : 28,
          "length" : 4
        },
        {
          "activity" : "generateNarratives",
          "start" : 30,
          "length" : 849
        },
        {
          "activity" : "validate",
          "start" : 45,
          "length" : 2091
        },
        {
          "activity" : "generate1",
          "start" : 48,
          "length" : 13
        },
        {
          "activity" : "generate2",
          "start" : 53,
          "length" : 14
        }
      ]
    },
    {
      "name" : "fsh-generated/resources/Patient-App1PatientExample.json",
      "size" : 800,
      "processes" : [
        {
          "activity" : "loadResources",
          "start" : 28,
          "length" : 7
        },
        {
          "activity" : "scan",
          "start" : 28,
          "length" : 1
        },
        {
          "activity" : "checkR4R4B",
          "start" : 28,
          "length" : 1
        },
        {
          "activity" : "generateNarratives",
          "start" : 31,
          "length" : 11
        },
        {
          "activity" : "validate",
          "start" : 47,
          "length" : 13
        },
        {
          "activity" : "generate1",
          "start" : 48,
          "length" : 12
        },
        {
          "activity" : "generate2",
          "start" : 53,
          "length" : 8
        }
      ]
    },
    {
      "name" : "fsh-generated/resources/Patient-App2PatientExample.json",
      "size" : 796,
      "processes" : [
        {
          "activity" : "loadResources",
          "start" : 28,
          "length" : 6
        },
        {
          "activity" : "load",
          "start" : 28,
          "length" : 1
        },
        {
          "activity" : "generateNarratives",
          "start" : 31,
          "length" : 6
        },
        {
          "activity" : "validate",
          "start" : 47,
          "length" : 15
        },
        {
          "activity" : "generate1",
          "start" : 48,
          "length" : 12
        },
        {
          "activity" : "generate2",
          "start" : 53,
          "length" : 10
        }
      ]
    },
    {
      "name" : "fsh-generated/resources/SearchParameter-UpdateDateSP.json",
      "size" : 616,
      "processes" : [
        {
          "activity" : "loadResources",
          "start" : 28,
          "length" : 8
        },
        {
          "activity" : "load",
          "start" : 28,
          "length" : 2
        },
        {
          "activity" : "load",
          "start" : 28,
          "length" : 3
        },
        {
          "activity" : "generateNarratives",
          "start" : 31,
          "length" : 14
        },
        {
          "activity" : "validate",
          "start" : 42,
          "length" : 10
        },
        {
          "activity" : "generate1",
          "start" : 48,
          "length" : 10
        },
        {
          "activity" : "generate2",
          "start" : 53,
          "length" : 13
        },
        {
          "activity" : "generateValidationPack",
          "start" : 65,
          "length" : 1
        }
      ]
    },
    {
      "name" : "fsh-generated/resources/StructureDefinition-App1Observation.json",
      "size" : 847,
      "processes" : [
        {
          "activity" : "loadResources",
          "start" : 28,
          "length" : 5
        },
        {
          "activity" : "load",
          "start" : 28,
          "length" : 2
        },
        {
          "activity" : "generateSnapshots",
          "start" : 28,
          "length" : 120
        },
        {
          "activity" : "loadInfo",
          "start" : 28,
          "length" : 1
        },
        {
          "activity" : "generateNarratives",
          "start" : 31,
          "length" : 83
        },
        {
          "activity" : "validate",
          "start" : 36,
          "length" : 555
        },
        {
          "activity" : "checkConformanceResources",
          "start" : 45,
          "length" : 1
        },
        {
          "activity" : "scanForUsageStats",
          "start" : 45,
          "length" : 2
        },
        {
          "activity" : "generate1",
          "start" : 48,
          "length" : 205
        },
        {
          "activity" : "generate2",
          "start" : 53,
          "length" : 2060
        },
        {
          "activity" : "generate2",
          "start" : 58,
          "length" : 987
        },
        {
          "activity" : "generateValidationPack",
          "start" : 65,
          "length" : 11
        },
        {
          "activity" : "scanProfilesForR5",
          "start" : 74,
          "length" : 1
        },
        {
          "activity" : "scanExamplesForR5",
          "start" : 74,
          "length" : 1
        }
      ]
    },
    {
      "name" : "fsh-generated/resources/StructureDefinition-App1Patient.json",
      "size" : 1122,
      "processes" : [
        {
          "activity" : "loadResources",
          "start" : 28,
          "length" : 4
        },
        {
          "activity" : "load",
          "start" : 28,
          "length" : 3
        },
        {
          "activity" : "generateSnapshots",
          "start" : 28,
          "length" : 108
        },
        {
          "activity" : "generateNarratives",
          "start" : 31,
          "length" : 46
        },
        {
          "activity" : "validate",
          "start" : 37,
          "length" : 304
        },
        {
          "activity" : "scanForUsageStats",
          "start" : 45,
          "length" : 1
        },
        {
          "activity" : "generate1",
          "start" : 48,
          "length" : 194
        },
        {
          "activity" : "generate2",
          "start" : 55,
          "length" : 394
        },
        {
          "activity" : "generate2",
          "start" : 59,
          "length" : 292
        },
        {
          "activity" : "generateValidationPack",
          "start" : 65,
          "length" : 9
        },
        {
          "activity" : "scanExamplesForR5",
          "start" : 74,
          "length" : 1
        }
      ]
    },
    {
      "name" : "fsh-generated/resources/StructureDefinition-App2Observation.json",
      "size" : 1286,
      "processes" : [
        {
          "activity" : "loadResources",
          "start" : 28,
          "length" : 4
        },
        {
          "activity" : "load",
          "start" : 28,
          "length" : 2
        },
        {
          "activity" : "generateSnapshots",
          "start" : 28,
          "length" : 34
        },
        {
          "activity" : "load-configure",
          "start" : 28,
          "length" : 2
        },
        {
          "activity" : "scan",
          "start" : 28,
          "length" : 1
        },
        {
          "activity" : "generateNarratives",
          "start" : 31,
          "length" : 36
        },
        {
          "activity" : "validate",
          "start" : 37,
          "length" : 275
        },
        {
          "activity" : "scanForUsageStats",
          "start" : 45,
          "length" : 1
        },
        {
          "activity" : "generate1",
          "start" : 48,
          "length" : 216
        },
        {
          "activity" : "generate2",
          "start" : 55,
          "length" : 1268
        },
        {
          "activity" : "generate2",
          "start" : 59,
          "length" : 260
        },
        {
          "activity" : "generateValidationPack",
          "start" : 65,
          "length" : 12
        },
        {
          "activity" : "scanExamplesForR5",
          "start" : 74,
          "length" : 1
        }
      ]
    },
    {
      "name" : "fsh-generated/resources/StructureDefinition-App2Patient.json",
      "size" : 1122,
      "processes" : [
        {
          "activity" : "loadResources",
          "start" : 28,
          "length" : 3
        },
        {
          "activity" : "load",
          "start" : 28,
          "length" : 3
        },
        {
          "activity" : "generateSnapshots",
          "start" : 28,
          "length" : 33
        },
        {
          "activity" : "generateNarratives",
          "start" : 31,
          "length" : 30
        },
        {
          "activity" : "validate",
          "start" : 37,
          "length" : 226
        },
        {
          "activity" : "generate1",
          "start" : 48,
          "length" : 194
        },
        {
          "activity" : "generate2",
          "start" : 56,
          "length" : 281
        },
        {
          "activity" : "generate2",
          "start" : 60,
          "length" : 184
        },
        {
          "activity" : "generateValidationPack",
          "start" : 65,
          "length" : 9
        },
        {
          "activity" : "scanExamplesForR5",
          "start" : 74,
          "length" : 1
        }
      ]
    },
    {
      "name" : "fsh-generated/resources/StructureDefinition-CoreObservation.json",
      "size" : 1274,
      "processes" : [
        {
          "activity" : "loadResources",
          "start" : 28,
          "length" : 5
        },
        {
          "activity" : "load",
          "start" : 28,
          "length" : 4
        },
        {
          "activity" : "generateNarratives",
          "start" : 31,
          "length" : 49
        },
        {
          "activity" : "validate",
          "start" : 38,
          "length" : 350
        },
        {
          "activity" : "scanForUsageStats",
          "start" : 45,
          "length" : 1
        },
        {
          "activity" : "generate1",
          "start" : 48,
          "length" : 239
        },
        {
          "activity" : "generate2",
          "start" : 57,
          "length" : 654
        },
        {
          "activity" : "generate2",
          "start" : 60,
          "length" : 186
        },
        {
          "activity" : "generateValidationPack",
          "start" : 65,
          "length" : 11
        },
        {
          "activity" : "scanExamplesForR5",
          "start" : 74,
          "length" : 1
        }
      ]
    },
    {
      "name" : "fsh-generated/resources/StructureDefinition-CorePatient.json",
      "size" : 2049,
      "processes" : [
        {
          "activity" : "loadResources",
          "start" : 28,
          "length" : 5
        },
        {
          "activity" : "load",
          "start" : 28,
          "length" : 4
        },
        {
          "activity" : "generateNarratives",
          "start" : 31,
          "length" : 35
        },
        {
          "activity" : "validate",
          "start" : 38,
          "length" : 294
        },
        {
          "activity" : "scanForUsageStats",
          "start" : 45,
          "length" : 1
        },
        {
          "activity" : "generate1",
          "start" : 49,
          "length" : 167
        },
        {
          "activity" : "generate2",
          "start" : 57,
          "length" : 449
        },
        {
          "activity" : "generate2",
          "start" : 60,
          "length" : 149
        },
        {
          "activity" : "makeDependencies",
          "start" : 62,
          "length" : 1
        },
        {
          "activity" : "generateValidationPack",
          "start" : 65,
          "length" : 8
        }
      ]
    },
    {
      "name" : "fsh-generated/resources/StructureDefinition-CreateDate.json",
      "size" : 1473,
      "processes" : [
        {
          "activity" : "loadResources",
          "start" : 28,
          "length" : 6
        },
        {
          "activity" : "load",
          "start" : 28,
          "length" : 2
        },
        {
          "activity" : "generateSnapshots",
          "start" : 28,
          "length" : 9
        },
        {
          "activity" : "generateNarratives",
          "start" : 31,
          "length" : 8
        },
        {
          "activity" : "validate",
          "start" : 38,
          "length" : 3461
        },
        {
          "activity" : "generate1",
          "start" : 49,
          "length" : 34
        },
        {
          "activity" : "generate2",
          "start" : 58,
          "length" : 117
        },
        {
          "activity" : "generate2",
          "start" : 60,
          "length" : 32
        },
        {
          "activity" : "generateValidationPack",
          "start" : 65,
          "length" : 1
        }
      ]
    },
    {
      "name" : "fsh-generated/resources/StructureDefinition-ObservationSource.json",
      "size" : 2498,
      "processes" : [
        {
          "activity" : "loadResources",
          "start" : 28,
          "length" : 4
        },
        {
          "activity" : "load",
          "start" : 28,
          "length" : 2
        },
        {
          "activity" : "generateSnapshots",
          "start" : 28,
          "length" : 9
        },
        {
          "activity" : "generateNarratives",
          "start" : 31,
          "length" : 8
        },
        {
          "activity" : "validate",
          "start" : 42,
          "length" : 34
        },
        {
          "activity" : "checkConformanceResources",
          "start" : 45,
          "length" : 1
        },
        {
          "activity" : "generate1",
          "start" : 49,
          "length" : 34
        },
        {
          "activity" : "generate2",
          "start" : 58,
          "length" : 110
        },
        {
          "activity" : "generate2",
          "start" : 60,
          "length" : 25
        },
        {
          "activity" : "generateValidationPack",
          "start" : 65,
          "length" : 1
        }
      ]
    },
    {
      "name" : "fsh-generated/resources/ValueSet-App1ObsCodeVS.json",
      "size" : 645,
      "processes" : [
        {
          "activity" : "loadResources",
          "start" : 28,
          "length" : 5
        },
        {
          "activity" : "load",
          "start" : 28,
          "length" : 4
        },
        {
          "activity" : "load-configure",
          "start" : 28,
          "length" : 1
        },
        {
          "activity" : "generateNarratives",
          "start" : 31,
          "length" : 933
        },
        {
          "activity" : "validate",
          "start" : 33,
          "length" : 1345
        },
        {
          "activity" : "generate1",
          "start" : 49,
          "length" : 12
        },
        {
          "activity" : "generate2",
          "start" : 58,
          "length" : 113
        }
      ]
    },
    {
      "name" : "fsh-generated/resources/ValueSet-App2ObsCatVS.json",
      "size" : 468,
      "processes" : [
        {
          "activity" : "loadResources",
          "start" : 28,
          "length" : 3
        },
        {
          "activity" : "load",
          "start" : 28,
          "length" : 3
        },
        {
          "activity" : "generateSnapshots",
          "start" : 28,
          "length" : 1
        },
        {
          "activity" : "checkR4R4B",
          "start" : 28,
          "length" : 1
        },
        {
          "activity" : "generateNarratives",
          "start" : 32,
          "length" : 426
        },
        {
          "activity" : "validate",
          "start" : 34,
          "length" : 907
        },
        {
          "activity" : "generate1",
          "start" : 49,
          "length" : 12
        },
        {
          "activity" : "generate2",
          "start" : 58,
          "length" : 51
        }
      ]
    },
    {
      "name" : "fsh-generated/resources/ValueSet-App2ObsCodeVS.json",
      "size" : 647,
      "processes" : [
        {
          "activity" : "loadResources",
          "start" : 28,
          "length" : 3
        },
        {
          "activity" : "load",
          "start" : 28,
          "length" : 3
        },
        {
          "activity" : "generateNarratives",
          "start" : 33,
          "length" : 431
        },
        {
          "activity" : "validate",
          "start" : 35,
          "length" : 795
        },
        {
          "activity" : "generate1",
          "start" : 49,
          "length" : 9
        },
        {
          "activity" : "generate2",
          "start" : 58,
          "length" : 51
        }
      ]
    },
    {
      "name" : "fsh-generated/resources/ValueSet-ObservationIdVS.json",
      "size" : 495,
      "processes" : [
        {
          "activity" : "loadResources",
          "start" : 28,
          "length" : 2
        },
        {
          "activity" : "load",
          "start" : 28,
          "length" : 3
        },
        {
          "activity" : "generateNarratives",
          "start" : 33,
          "length" : 4
        },
        {
          "activity" : "validate",
          "start" : 36,
          "length" : 9
        },
        {
          "activity" : "generate1",
          "start" : 49,
          "length" : 9
        },
        {
          "activity" : "generate2",
          "start" : 58,
          "length" : 42
        },
        {
          "activity" : "generateValidationPack",
          "start" : 65,
          "length" : 1
        },
        {
          "activity" : "scanExamplesForR5",
          "start" : 74,
          "length" : 1
        }
      ]
    },
    {
      "name" : "fsh-generated/resources/ValueSet-PatientIdVS.json",
      "size" : 549,
      "processes" : [
        {
          "activity" : "loadResources",
          "start" : 28,
          "length" : 3
        },
        {
          "activity" : "load",
          "start" : 28,
          "length" : 4
        },
        {
          "activity" : "generateNarratives",
          "start" : 33,
          "length" : 4
        },
        {
          "activity" : "validate",
          "start" : 36,
          "length" : 7
        },
        {
          "activity" : "generate1",
          "start" : 49,
          "length" : 10
        },
        {
          "activity" : "generate2",
          "start" : 58,
          "length" : 38
        }
      ]
    },
    {
      "name" : "/fsh-generated/includes/fsh-link-references.md",
      "size" : 1124,
      "processes" : [
        {
          "activity" : "generate2",
          "start" : 58,
          "length" : 1
        }
      ]
    },
    {
      "name" : "/fsh-generated/includes/menu.xml",
      "size" : 1797
    },
    {
      "name" : "/input/pagecontent/app2.md",
      "size" : 49
    },
    {
      "name" : "/input/pagecontent/profiles.md",
      "size" : 261
    },
    {
      "name" : "/input/pagecontent/terminology.md",
      "size" : 256
    },
    {
      "name" : "/input/pagecontent/app1.md",
      "size" : 98,
      "processes" : [
        {
          "activity" : "generate2",
          "start" : 58,
          "length" : 1
        }
      ]
    },
    {
      "name" : "/input/pagecontent/index.md",
      "size" : 6609
    },
    {
      "name" : "/template/config",
      "size" : 0
    },
    {
      "name" : "/template/config/_config.yml",
      "size" : 140
    },
    {
      "name" : "/input/images",
      "size" : 0
    },
    {
      "name" : "/input/images/logo.png",
      "size" : 53942,
      "processes" : [
        {
          "activity" : "generate2",
          "start" : 58,
          "length" : 1
        }
      ]
    },
    {
      "name" : "/input/images/workflow.png",
      "size" : 238884
    },
    {
      "name" : "/input/images/architecture.png",
      "size" : 71752
    },
    {
      "name" : "/temp/pages/_includes/artifacts.xml",
      "size" : 12229,
      "processes" : [
        {
          "activity" : "generate2",
          "start" : 58,
          "length" : 1
        }
      ]
    }
  ]
}
